simultipac/__init__.py
simultipac/constants.py
simultipac/types.py
simultipac/cst/__init__.py
simultipac/cst/helper.py
simultipac/cst/simulation_results.py
simultipac/particle_monitor/__init__.py
simultipac/particle_monitor/converters.py
simultipac/particle_monitor/particle.py
simultipac/particle_monitor/particle_monitor.py
simultipac/particle_monitor/vector.py
simultipac/particle_monitor/collisions/__init__.py
simultipac/particle_monitor/collisions/util.py
simultipac/particle_monitor/collisions/vedo_mesh_collisions.py
simultipac/plotter/__init__.py
simultipac/plotter/default.py
simultipac/plotter/plotter.py
simultipac/simulation_results/__init__.py
simultipac/simulation_results/simulation_results.py
simultipac/simulation_results/simulations_results.py
simultipac/spark3d/__init__.py
simultipac/spark3d/simulation_results.py
simultipac/util/__init__.py
simultipac/util/exponential_growth.py
simultipac/util/log_manager.py
simultipac/util/singleton.py
simultipac-2.1.0.dist-info/licenses/LICENSE
simultipac-2.1.0.dist-info/METADATA
simultipac-2.1.0.dist-info/WHEEL
simultipac-2.1.0.dist-info/top_level.txt
simultipac-2.1.0.dist-info/RECORD
