Metadata-Version: 2.4
Name: Simultipac
Version: 2.1.0
Summary: Treat data from CST Particle Studio and SPARK3D for multipactor
Author-email: Adrien Plaçais <placais@lpsc.in2p3.fr>
Project-URL: changelog, https://github.com/AdrienPlacais/Simulia_Multipactor_lib/blob/main/CHANGELOG.md
Project-URL: documentation, https://simultipac.readthedocs.io/en/latest/
Project-URL: homepage, https://github.com/AdrienPlacais/Simulia_Multipactor_lib
Project-URL: tracker, https://github.com/AdrienPlacais/Simulia_Multipactor_lib/issues
Classifier: Development Status :: 3 - Alpha
Classifier: Intended Audience :: Science/Research
Classifier: License :: OSI Approved :: MIT License
Classifier: Operating System :: OS Independent
Classifier: Programming Language :: Python :: 3.12
Classifier: Topic :: Scientific/Engineering :: Physics
Requires-Python: >=3.12
License-File: LICENSE
Requires-Dist: matplotlib<4,>=3.9.1
Requires-Dist: numpy<3,>=2
Requires-Dist: pandas<3,>=2.2
Requires-Dist: palettable<4,>=3.3.3
Requires-Dist: pre-commit<5,>=4
Requires-Dist: scipy<2,>=1.15
Requires-Dist: vedo<2026,>=2025.5
Provides-Extra: docs
Requires-Dist: myst-parser<5,>=4; extra == "docs"
Requires-Dist: nbsphinx<1,>=0.9.6; extra == "docs"
Requires-Dist: sphinx-autodoc-typehints<4,>=3.0.1; extra == "docs"
Requires-Dist: sphinx-rtd-theme<4,>=3; extra == "docs"
Requires-Dist: sphinx-tabs<4,>=3.4; extra == "docs"
Requires-Dist: sphinxcontrib-bibtex<3,>=2.6; extra == "docs"
Provides-Extra: k3d
Requires-Dist: jupyter; extra == "k3d"
Requires-Dist: k3d<3,>=2.16; extra == "k3d"
Requires-Dist: notebook<8,>=7; extra == "k3d"
Provides-Extra: test
Requires-Dist: pytest<9,>=8.3.2; extra == "test"
Requires-Dist: pytest-mock<4,>=3.14; extra == "test"
Dynamic: license-file
